{"resource": "commonplayerinfo", "parameters": [{"PlayerID": 998}, {"LeagueID": "00"}], "resultSets": [{"name": "CommonPlayerInfo", "headers": ["PERSON_ID", "FIRST_NAME", "LAST_NAME", "DISPLAY_FIRST_LAST", "DISPLAY_LAST_COMMA_FIRST", "DISPLAY_FI_LAST", "PLAYER_SLUG", "BIRTHDATE", "SCHOOL", "COUNTRY", "LAST_AFFILIATION", "HEIGHT", "WEIGHT", "SEASON_EXP", "JERSEY", "POSITION", "ROSTERSTATUS", "GAMES_PLAYED_CURRENT_SEASON_FLAG", "TEAM_ID", "TEAM_NAME", "TEAM_ABBREVIATION", "TEAM_CODE", "TEAM_CITY", "PLAYERCODE", "FROM_YEAR", "TO_YEAR", "DLEAGUE_FLAG", "NBA_FLAG", "GAMES_PLAYED_FLAG", "DRAFT_YEAR", "DRAFT_ROUND", "DRAFT_NUMBER", "GREATEST_75_FLAG"], "rowSet": [[998, "Mark", "Pope", "Mark Pope", "Pope, Mark", "M. Pope", "mark-pope", "1972-09-11T00:00:00", "Kentucky", "USA", "Kentucky/USA", "6-10", "235", 7, "41", "Center-Forward", "Inactive", "N", 1610612749, "Bucks", "MIL", "bucks", "Milwaukee", "mark_pope", 1997, 2004, "N", "Y", "Y", "1996", "2", "52", "N"]]}, {"name": "PlayerHeadlineStats", "headers": ["PLAYER_ID", "PLAYER_NAME", "TimeFrame", "PTS", "AST", "REB", "ALL_STAR_APPEARANCES"], "rowSet": [[998, "Mark Pope", "career", 1.9, 0.4, 1.7, 0]]}, {"name": "AvailableSeasons", "headers": ["SEASON_ID"], "rowSet": [["11997"], ["21997"], ["41997"], ["11998"], ["21998"], ["12000"], ["22000"], ["42000"], ["12001"], ["22001"], ["12002"], ["12003"], ["22003"], ["12004"], ["22004"], ["12005"]]}]}