{"resource": "commonplayerinfo", "parameters": [{"PlayerID": 713}, {"LeagueID": "00"}], "resultSets": [{"name": "CommonPlayerInfo", "headers": ["PERSON_ID", "FIRST_NAME", "LAST_NAME", "DISPLAY_FIRST_LAST", "DISPLAY_LAST_COMMA_FIRST", "DISPLAY_FI_LAST", "PLAYER_SLUG", "BIRTHDATE", "SCHOOL", "COUNTRY", "LAST_AFFILIATION", "HEIGHT", "WEIGHT", "SEASON_EXP", "JERSEY", "POSITION", "ROSTERSTATUS", "GAMES_PLAYED_CURRENT_SEASON_FLAG", "TEAM_ID", "TEAM_NAME", "TEAM_ABBREVIATION", "TEAM_CODE", "TEAM_CITY", "PLAYERCODE", "FROM_YEAR", "TO_YEAR", "DLEAGUE_FLAG", "NBA_FLAG", "GAMES_PLAYED_FLAG", "DRAFT_YEAR", "DRAFT_ROUND", "DRAFT_NUMBER", "GREATEST_75_FLAG"], "rowSet": [[713, "Chris", "Carr", "Chris Carr", "Carr, Chris", "C. Carr", "chris-carr", "1974-03-12T00:00:00", "Southern Illinois", "USA", "Southern Illinois/USA", "6-6", "220", 7, "", "Guard", "Inactive", "N", 0, "", "", "", "", "chris_carr", 1995, 2000, "N", "Y", "Y", "1995", "2", "56", "N"]]}, {"name": "PlayerHeadlineStats", "headers": ["PLAYER_ID", "PLAYER_NAME", "TimeFrame", "PTS", "AST", "REB", "ALL_STAR_APPEARANCES"], "rowSet": [[713, "Chris Carr", "career", 6.7, 1.0, 2.2, 0]]}, {"name": "AvailableSeasons", "headers": ["SEASON_ID"], "rowSet": [["21995"], ["41995"], ["21996"], ["41996"], ["11997"], ["21997"], ["11998"], ["21998"], ["21999"], ["12000"], ["22000"]]}]}